MANIFEST.in
README.rst
setup.py
collective/__init__.py
collective.periodcriterion.egg-info/PKG-INFO
collective.periodcriterion.egg-info/SOURCES.txt
collective.periodcriterion.egg-info/dependency_links.txt
collective.periodcriterion.egg-info/entry_points.txt
collective.periodcriterion.egg-info/namespace_packages.txt
collective.periodcriterion.egg-info/not-zip-safe
collective.periodcriterion.egg-info/requires.txt
collective.periodcriterion.egg-info/top_level.txt
collective/periodcriterion/__init__.py
collective/periodcriterion/config.py
collective/periodcriterion/configure.zcml
collective/periodcriterion/criteria.py
collective/periodcriterion/interfaces.py
collective/periodcriterion/queryparser.py
collective/periodcriterion/tests.py
collective/periodcriterion/Extensions/install.py
collective/periodcriterion/locales/collective.periodcriterion-manual.pot
collective/periodcriterion/locales/collective.periodcriterion.pot
collective/periodcriterion/locales/run18ndude.sh
collective/periodcriterion/locales/it/LC_MESSAGES/collective.periodcriterion.po
collective/periodcriterion/profiles/default/metadata.xml
collective/periodcriterion/profiles/default/portal_atct.xml
collective/periodcriterion/profiles/default/registry.xml
collective/periodcriterion/profiles/default/rolemap.xml
collective/periodcriterion/profiles/default/types.xml
collective/periodcriterion/profiles/default/types/ATPeriodCriteria.xml
collective/periodcriterion/profiles/uninstall/registry.xml
docs/HISTORY.txt
docs/INSTALL.txt
docs/LICENSE.GPL
docs/LICENSE.txt