Metadata-Version: 1.0
Name: collective.periodcriterion
Version: 0.2.0
Summary: Add to Plone Collection content type the "this month" and "this year" criteria
Home-page: http://plone.org/products/collective.periodcriterion
Author: RedTurtle Technology
Author-email: sviluppoplone@redturtle.it
License: GPL
Keywords: plone plonegov collection criterion
Platform: UNKNOWN
Classifier: Framework :: Plone
Classifier: Framework :: Plone :: 4.2
Classifier: Framework :: Plone :: 4.3
Classifier: Programming Language :: Python
Classifier: Development Status :: 4 - Beta
